pysmaz/__init__.py
pysmaz/backends/__init__.py
pysmaz/backends/cffi/__init__.py
pysmaz/backends/cffi/build.py
pysmaz/backends/cffi/_smaz.abi3.so
pysmaz/backends/cython/_smaz.pyx
pysmaz/backends/cython/_smaz.c
pysmaz/backends/cython/smaz.pxd
pysmaz/backends/cython/__init__.py
pysmaz/backends/cython/_smaz.abi3.so
python_smaz-0.1.2.dist-info/top_level.txt
python_smaz-0.1.2.dist-info/METADATA
python_smaz-0.1.2.dist-info/WHEEL
python_smaz-0.1.2.dist-info/RECORD
